{
	"info": {
		"_postman_id": "7fff0574-5ff7-4480-a30f-b0c4f18b06a5",
		"name": "API-FREELANCE",
		"schema": "https://schema.getpostman.com/json/collection/v2.1.0/collection.json",
		"_exporter_id": "11940030",
		"_collection_link": "https://red-star-88223.postman.co/workspace/INFNET~4b9da1d9-6e9f-4859-a252-aca8cdd5a28a/collection/11940030-7fff0574-5ff7-4480-a30f-b0c4f18b06a5?action=share&source=collection_link&creator=11940030"
	},
	"item": [
		{
			"name": "auth",
			"item": [
				{
					"name": "auth.signIn",
					"event": [
						{
							"listen": "test",
							"script": {
								"exec": [
									""
								],
								"type": "text/javascript"
							}
						},
						{
							"listen": "prerequest",
							"script": {
								"exec": [
									""
								],
								"type": "text/javascript"
							}
						}
					],
					"request": {
						"auth": {
							"type": "bearer",
							"bearer": [
								{
									"key": "token",
									"value": "eyJhbGciOiJIUzI1NiIsInR5cCI6IkpXVCJ9.eyJlbWFpbCI6ImRhbmllbEBnbWFpbC5jb20iLCJuYW1lIjoiRGFuaWVsIEJhcmJvemEiLCJ0eXBlIjoxLCJpYXQiOjE2NTQ0ODI5MjIsImV4cCI6MTY2MzQ4MjkyMn0.wwm5ffUkQjtISWJqQhxKy2xQ_VQfbOxJoV6QbN561h4",
									"type": "string"
								}
							]
						},
						"method": "POST",
						"header": [],
						"body": {
							"mode": "raw",
							"raw": "{\n    \"username\": \"daniel95barboza\",\n    \"password\": \"123\"\n}",
							"options": {
								"raw": {
									"language": "json"
								}
							}
						},
						"url": {
							"raw": "http://localhost:3011/auth",
							"protocol": "http",
							"host": [
								"localhost"
							],
							"port": "3011",
							"path": [
								"auth"
							]
						}
					},
					"response": []
				},
				{
					"name": "auth.logout",
					"event": [
						{
							"listen": "test",
							"script": {
								"exec": [
									""
								],
								"type": "text/javascript"
							}
						},
						{
							"listen": "prerequest",
							"script": {
								"exec": [
									""
								],
								"type": "text/javascript"
							}
						}
					],
					"request": {
						"auth": {
							"type": "bearer",
							"bearer": [
								{
									"key": "token",
									"value": "eyJhbGciOiJIUzI1NiIsInR5cCI6IkpXVCJ9.eyJlbWFpbCI6ImRhbmllbEBnbWFpbC5jb20iLCJuYW1lIjoiRGFuaWVsIEJhcmJvemEiLCJ0eXBlIjoxLCJpYXQiOjE2NTQ0ODI5MjIsImV4cCI6MTY2MzQ4MjkyMn0.wwm5ffUkQjtISWJqQhxKy2xQ_VQfbOxJoV6QbN561h4",
									"type": "string"
								}
							]
						},
						"method": "POST",
						"header": [],
						"body": {
							"mode": "raw",
							"raw": "{\n    \"email\": \"daniel95barboza@gmail.com\",\n    \"password\": \"daniel\"\n}",
							"options": {
								"raw": {
									"language": "json"
								}
							}
						},
						"url": {
							"raw": "http://localhost:3011/logout",
							"protocol": "http",
							"host": [
								"localhost"
							],
							"port": "3011",
							"path": [
								"logout"
							]
						}
					},
					"response": []
				},
				{
					"name": "auth.register",
					"event": [
						{
							"listen": "test",
							"script": {
								"exec": [
									""
								],
								"type": "text/javascript"
							}
						},
						{
							"listen": "prerequest",
							"script": {
								"exec": [
									""
								],
								"type": "text/javascript"
							}
						}
					],
					"request": {
						"auth": {
							"type": "bearer",
							"bearer": [
								{
									"key": "token",
									"value": "eyJhbGciOiJIUzI1NiIsInR5cCI6IkpXVCJ9.eyJlbWFpbCI6ImRhbmllbEBnbWFpbC5jb20iLCJuYW1lIjoiRGFuaWVsIEJhcmJvemEiLCJ0eXBlIjoxLCJpYXQiOjE2NTQ0ODI5MjIsImV4cCI6MTY2MzQ4MjkyMn0.wwm5ffUkQjtISWJqQhxKy2xQ_VQfbOxJoV6QbN561h4",
									"type": "string"
								}
							]
						},
						"method": "POST",
						"header": [],
						"body": {
							"mode": "formdata",
							"formdata": [
								{
									"key": "username",
									"value": "jose172d",
									"type": "text"
								},
								{
									"key": "email",
									"value": "josed@gmail.com",
									"type": "text"
								},
								{
									"key": "password",
									"value": "123",
									"type": "text"
								},
								{
									"key": "country",
									"value": "brasil",
									"type": "text"
								},
								{
									"key": "name",
									"value": "Jose Carlos",
									"type": "text"
								},
								{
									"key": "cpf",
									"value": "333.222.333-33",
									"type": "text"
								},
								{
									"key": "birthDate",
									"value": "20200404",
									"type": "text"
								},
								{
									"key": "files",
									"type": "file",
									"src": "/C:/Users/pc-02/Downloads/1111.jpeg"
								},
								{
									"key": "phone",
									"value": "(21)99999-9999",
									"type": "text"
								},
								{
									"key": "desc",
									"value": "Desenvolvedor backend",
									"type": "text"
								},
								{
									"key": "isSeller",
									"value": "false",
									"type": "text"
								}
							]
						},
						"url": {
							"raw": "http://localhost:3011/register",
							"protocol": "http",
							"host": [
								"localhost"
							],
							"port": "3011",
							"path": [
								"register"
							]
						}
					},
					"response": []
				}
			]
		},
		{
			"name": "conversation",
			"item": [
				{
					"name": "conversation.create",
					"request": {
						"auth": {
							"type": "bearer",
							"bearer": [
								{
									"key": "token",
									"value": "eyJhbGciOiJIUzI1NiIsInR5cCI6IkpXVCJ9.eyJlbWFpbCI6ImRhbmllbEBnbWFpbC5jb20iLCJuYW1lIjoiRGFuaWVsIEJhcmJvemEiLCJ0eXBlIjoxLCJpYXQiOjE2NTQ0ODI5MjIsImV4cCI6MTY2MzQ4MjkyMn0.wwm5ffUkQjtISWJqQhxKy2xQ_VQfbOxJoV6QbN561h4",
									"type": "string"
								}
							]
						},
						"method": "POST",
						"header": [
							{
								"key": "token",
								"value": "{{token}}",
								"type": "text"
							}
						],
						"body": {
							"mode": "raw",
							"raw": "{\r\n    \"isSeller\": true,\r\n    \"userId\": \"657f13cfc2311d6aac6e0d95\",\r\n    \"to\": \"657f6e7b82ee85e39b6e0f18\"\r\n}",
							"options": {
								"raw": {
									"language": "json"
								}
							}
						},
						"url": {
							"raw": "http://localhost:3011/conversation",
							"protocol": "http",
							"host": [
								"localhost"
							],
							"port": "3011",
							"path": [
								"conversation"
							]
						}
					},
					"response": []
				},
				{
					"name": "conversation.listAll",
					"protocolProfileBehavior": {
						"disableBodyPruning": true
					},
					"request": {
						"auth": {
							"type": "bearer",
							"bearer": [
								{
									"key": "token",
									"value": "eyJhbGciOiJIUzI1NiIsInR5cCI6IkpXVCJ9.eyJlbWFpbCI6ImRhbmllbEBnbWFpbC5jb20iLCJuYW1lIjoiRGFuaWVsIEJhcmJvemEiLCJ0eXBlIjoxLCJpYXQiOjE2NTQ0ODI5MjIsImV4cCI6MTY2MzQ4MjkyMn0.wwm5ffUkQjtISWJqQhxKy2xQ_VQfbOxJoV6QbN561h4",
									"type": "string"
								}
							]
						},
						"method": "GET",
						"header": [
							{
								"key": "token",
								"value": "{{token}}",
								"type": "text"
							}
						],
						"body": {
							"mode": "raw",
							"raw": "{\r\n    \"isSeller\": true,\r\n    \"userId\": \"657f13cfc2311d6aac6e0d95\"\r\n}",
							"options": {
								"raw": {
									"language": "json"
								}
							}
						},
						"url": {
							"raw": "http://localhost:3011/conversation",
							"protocol": "http",
							"host": [
								"localhost"
							],
							"port": "3011",
							"path": [
								"conversation"
							]
						}
					},
					"response": []
				},
				{
					"name": "category.listById",
					"request": {
						"auth": {
							"type": "bearer",
							"bearer": [
								{
									"key": "token",
									"value": "eyJhbGciOiJIUzI1NiIsInR5cCI6IkpXVCJ9.eyJlbWFpbCI6ImRhbmllbEBnbWFpbC5jb20iLCJuYW1lIjoiRGFuaWVsIEJhcmJvemEiLCJ0eXBlIjoxLCJpYXQiOjE2NTQ0ODI5MjIsImV4cCI6MTY2MzQ4MjkyMn0.wwm5ffUkQjtISWJqQhxKy2xQ_VQfbOxJoV6QbN561h4",
									"type": "string"
								}
							]
						},
						"method": "GET",
						"header": [
							{
								"key": "token",
								"value": "{{token}}",
								"type": "text"
							}
						],
						"url": {
							"raw": "http://localhost:3011/category/6320f577156b47ff1082586e",
							"protocol": "http",
							"host": [
								"localhost"
							],
							"port": "3011",
							"path": [
								"category",
								"6320f577156b47ff1082586e"
							]
						}
					},
					"response": []
				},
				{
					"name": "category.create",
					"event": [
						{
							"listen": "test",
							"script": {
								"exec": [
									""
								],
								"type": "text/javascript"
							}
						},
						{
							"listen": "prerequest",
							"script": {
								"exec": [
									""
								],
								"type": "text/javascript"
							}
						}
					],
					"request": {
						"method": "POST",
						"header": [
							{
								"key": "token",
								"value": "{{token}}",
								"type": "text"
							}
						],
						"body": {
							"mode": "formdata",
							"formdata": [
								{
									"key": "name",
									"value": "asdasdasdasd",
									"type": "text"
								},
								{
									"key": "code",
									"value": "12531642142335131",
									"type": "text"
								},
								{
									"key": "files",
									"type": "file",
									"src": "/C:/Users/pc01/Downloads/Logo para consultor de moedas e investimentos digitais verde tecnológico (1).png"
								}
							]
						},
						"url": {
							"raw": "http://localhost:3011/category",
							"protocol": "http",
							"host": [
								"localhost"
							],
							"port": "3011",
							"path": [
								"category"
							]
						}
					},
					"response": []
				},
				{
					"name": "category.update",
					"event": [
						{
							"listen": "test",
							"script": {
								"exec": [
									""
								],
								"type": "text/javascript"
							}
						},
						{
							"listen": "prerequest",
							"script": {
								"exec": [
									""
								],
								"type": "text/javascript"
							}
						}
					],
					"request": {
						"method": "PUT",
						"header": [
							{
								"key": "token",
								"value": "{{token}}",
								"type": "text"
							}
						],
						"body": {
							"mode": "formdata",
							"formdata": [
								{
									"key": "name",
									"value": "Smartphonesddddd",
									"type": "text"
								},
								{
									"key": "code",
									"value": "12531642142335131",
									"type": "text"
								},
								{
									"key": "files",
									"type": "file",
									"src": "/C:/Users/pc01/Pictures/maxresdefault.jpg"
								}
							]
						},
						"url": {
							"raw": "http://localhost:3011/category/63cabf4eb2f75d39dc221a60",
							"protocol": "http",
							"host": [
								"localhost"
							],
							"port": "3011",
							"path": [
								"category",
								"63cabf4eb2f75d39dc221a60"
							]
						}
					},
					"response": []
				},
				{
					"name": "category.delete",
					"event": [
						{
							"listen": "test",
							"script": {
								"exec": [
									""
								],
								"type": "text/javascript"
							}
						},
						{
							"listen": "prerequest",
							"script": {
								"exec": [
									""
								],
								"type": "text/javascript"
							}
						}
					],
					"request": {
						"method": "DELETE",
						"header": [
							{
								"key": "token",
								"value": "{{token}}",
								"type": "text"
							}
						],
						"body": {
							"mode": "urlencoded",
							"urlencoded": [
								{
									"key": "name",
									"value": "Teclado Dell",
									"type": "text"
								},
								{
									"key": "code",
									"value": "43242342342343224",
									"type": "text"
								}
							]
						},
						"url": {
							"raw": "http://localhost:3011/category/63cabf4eb2f75d39dc221a60",
							"protocol": "http",
							"host": [
								"localhost"
							],
							"port": "3011",
							"path": [
								"category",
								"63cabf4eb2f75d39dc221a60"
							]
						}
					},
					"response": []
				}
			]
		}
	]
}